<hwlcd>
<PanelEntry>
	<PanelCompatible>"100_704_6p756"</PanelCompatible>
	<PanelName>"100 704 0 6.756' 1344 x 2772"</PanelName>
	<!--lcdtype: amoled_2, lcd_1-->
	<PanelType>0x02</PanelType>
	<PanelXres>1344</PanelXres>
	<PanelYres>2772</PanelYres>
	<PanelWidth>74</PanelWidth>
	<PanelHeight>154</PanelHeight>

	<!-- Panel Command information -->
	<PanelOnCommand>"0x39, 0x01, 0x00, 0x00, 0x0a, 0x00, 0x03, 0x7F, 0x5A, 0x5A
			0x39, 0x01, 0x00, 0x00, 0x0a, 0x00, 0x03, 0xF0, 0x5A, 0x5A
			0x39, 0x01, 0x00, 0x00, 0x0a, 0x00, 0x03, 0xF1, 0x5A, 0x5A
			0x39, 0x01, 0x00, 0x00, 0x0a, 0x00, 0x03, 0xF2, 0x5A, 0x5A
			0x15, 0x01, 0x00, 0x00, 0x0a, 0x00, 0x02, 0x02, 0x01
			0x15, 0x01, 0x00, 0x00, 0x0a, 0x00, 0x02, 0x59, 0x00
			0x39, 0x01, 0x00, 0x00, 0x0a, 0x00, 0x05, 0x2A, 0x00, 0x00, 0x05, 0x3F
			0x39, 0x01, 0x00, 0x00, 0x0a, 0x00, 0x05, 0x2B, 0x00, 0x00, 0x0A, 0xD3
			0x39, 0x01, 0x00, 0x00, 0x0a, 0x00, 0x03, 0x51, 0x00, 0x00
			0x15, 0x01, 0x00, 0x00, 0x0a, 0x00, 0x02, 0x53, 0x20
			0x39, 0x01, 0x00, 0x00, 0x0a, 0x00, 0x08, 0x57, 0x00, 0x00, 0x01, 0xF8, 0xFF, 0xF0, 0x00
			0x39, 0x01, 0x00, 0x00, 0x0a, 0x00, 0x07, 0x58, 0x00, 0x00, 0x01, 0xF8, 0xFF, 0xF0
			0x15, 0x01, 0x00, 0x00, 0x0a, 0x00, 0x02, 0x76, 0x00
			0x15, 0x01, 0x00, 0x00, 0x0a, 0x00, 0x02, 0x35, 0x00
			0x05, 0x01, 0x00, 0x00, 0x5a, 0x01, 0x01, 0x11
			0x0A, 0x01, 0x00, 0x00, 0x01, 0x01, 0x80, 0x11, 0x00, 0x00, 0x89, 0x30, 0x80, 0x0A, 0xD4, 0x05, 0x40, 0x00, 0x24, 0x02, 0xA0, 0x02, 0xA0, 0x02, 0x00, 0x02, 0x50, 0x00, 0x20, 0x03, 0xDB, 0x00, 0x09, 0x00, 0x0C, 0x02, 0xBF, 0x02, 0x46, 0x18, 0x00, 0x10, 0xF0, 0x03, 0x0C, 0x20, 0x00, 0x06, 0x0B, 0x0B, 0x33, 0x0E, 0x1C, 0x2A, 0x38, 0x46, 0x54, 0x62, 0x69, 0x70, 0x77, 0x79, 0x7B, 0x7D, 0x7E, 0x01, 0x02, 0x01, 0x00, 0x09, 0x40, 0x09, 0xBE, 0x19, 0xFC, 0x19, 0xFA, 0x19, 0xF8, 0x1A, 0x38, 0x1A, 0x78, 0x1A, 0xB6, 0x2A, 0xF6, 0x2B, 0x34, 0x2B, 0x74, 0x3B, 0x74, 0x6B, 0xF4, 0x00, 0x00, 0x00, 0x00, 0x00, 0x00, 0x00, 0x00, 0x00, 0x00, 0x00, 0x00, 0x00, 0x00, 0x00, 0x00, 0x00, 0x00, 0x00, 0x00, 0x00, 0x00, 0x00, 0x00, 0x00, 0x00, 0x00, 0x00, 0x00, 0x00, 0x00, 0x00, 0x00, 0x00, 0x00, 0x00, 0x00, 0x00, 0x00, 0x00
			0x15, 0x01, 0x00, 0x00, 0x0a, 0x00, 0x02, 0xB0, 0xE9
			0x39, 0x01, 0x00, 0x00, 0x0a, 0x00, 0x0D, 0xC0, 0x60, 0x80, 0x60, 0x70, 0x80, 0x70, 0x80, 0x60, 0x80, 0x80, 0x60, 0x80
			0x15, 0x01, 0x00, 0x00, 0x0a, 0x00, 0x02, 0xB0, 0x70
			0x15, 0x01, 0x00, 0x00, 0x0a, 0x00, 0x02, 0xEC, 0x01
			0x15, 0x01, 0x00, 0x00, 0x0a, 0x00, 0x02, 0xB0, 0x09
			0x15, 0x01, 0x00, 0x00, 0x0a, 0x00, 0x02, 0xEA, 0x81
			0x15, 0x01, 0x00, 0x00, 0x0a, 0x00, 0x02, 0xB0, 0xD8
			0x39, 0x01, 0x00, 0x00, 0x0a, 0x00, 0x03, 0xE5, 0x80, 0x40
			0x15, 0x01, 0x00, 0x00, 0x0a, 0x00, 0x02, 0xB0, 0x05
			0x15, 0x01, 0x00, 0x00, 0x0a, 0x00, 0x02, 0xE5, 0x60
			0x15, 0x01, 0x00, 0x00, 0x0a, 0x00, 0x02, 0xB0, 0x08
			0x15, 0x01, 0x00, 0x00, 0x0a, 0x00, 0x02, 0xE5, 0x0D
			0x15, 0x01, 0x00, 0x00, 0x0a, 0x00, 0x02, 0xB0, 0x0B
			0x39, 0x01, 0x00, 0x00, 0x0a, 0x00, 0x03, 0xEA, 0xFF, 0xFF
			0x15, 0x01, 0x00, 0x00, 0x0a, 0x00, 0x02, 0xB0, 0x4C
			0x15, 0x01, 0x00, 0x00, 0x0a, 0x00, 0x02, 0xE0, 0x00
			0x15, 0x01, 0x00, 0x00, 0x0a, 0x00, 0x02, 0xB0, 0x01
			0x15, 0x01, 0x00, 0x00, 0x0a, 0x00, 0x02, 0xE0, 0x58
			0x39, 0x01, 0x00, 0x00, 0x0a, 0x00, 0x05, 0xE5, 0x00, 0xA4, 0x0A, 0xF0
			0x39, 0x01, 0x00, 0x00, 0x0a, 0x00, 0x03, 0xF0, 0xA5, 0xA5
			0x39, 0x01, 0x00, 0x00, 0x0a, 0x00, 0x03, 0xF1, 0xA5, 0xA5
			0x39, 0x01, 0x00, 0x00, 0x0a, 0x00, 0x03, 0xF2, 0xA5, 0xA5
			0x05, 0x01, 0x00, 0x00, 0x0a, 0x00, 0x01, 0x29"</PanelOnCommand>

	<PanelDisplayOnCommand>"0x05, 0x01, 0x00, 0x00, 0x78, 0x00, 0x01, 0x29"</PanelDisplayOnCommand>

	<PanelOffCommand>"0x05, 0x01, 0x00, 0x00, 0x0a, 0x00, 0x01, 0x28
			0x05, 0x01, 0x00, 0x00, 0x78, 0x01, 0x01, 0x10"</PanelOffCommand>
	<PanelOffCommandState>0</PanelOffCommandState>

	<PanelBacklightCommand>"0x39, 0x01, 0x00, 0x00, 0x00, 0x00, 0x03, 0x51, 0x00, 0x00"</PanelBacklightCommand>

	<!-- Panel Hbm cmd -->
	<PanelHbmEnterCommand>"0x39, 0x01, 0x00, 0x00, 0x0a, 0x00, 0x03, 0x51, 0x0F, 0xFF"</PanelHbmEnterCommand>

	<PanelHbmCommand>"0x39, 0x01, 0x00, 0x00, 0x0a, 0x00, 0x03, 0x51, 0x00, 0x00"</PanelHbmCommand>

	<PanelHbmExitCommand>"0x39, 0x01, 0x00, 0x00, 0x0a, 0x00, 0x03, 0x51, 0x00, 0x00"</PanelHbmExitCommand>

	<PanelFpEnterExCommand>"0x39, 0x01, 0x00, 0x00, 0x0a, 0x00, 0x03, 0x51, 0x07, 0xFF"</PanelFpEnterExCommand>

	<!-- Panel Acl cmd -->
	<PanelAclOffCommand>"0x15, 0x01, 0x00, 0x00, 0x0a, 0x00, 0x02, 0x55, 0x00"</PanelAclOffCommand>

	<PanelAclLowCommand>"0x15, 0x01, 0x00, 0x00, 0x0a, 0x00, 0x02, 0x55, 0x06"</PanelAclLowCommand>

	<PanelAclMiddleCommand>"0x15, 0x01, 0x00, 0x00, 0x0a, 0x00, 0x02, 0x55, 0x05"</PanelAclMiddleCommand>

	<PanelAclHighCommand>"0x15, 0x01, 0x00, 0x00, 0x0a, 0x00, 0x02, 0x55, 0x04"</PanelAclHighCommand>

	<!-- Panel Aod cmd -->
	<PanelAodEnterCommand>"0x05, 0x01, 0x00, 0x00, 0x0a, 0x00, 0x01, 0x28
			0x05, 0x01, 0x00, 0x00, 0x1e, 0x01, 0x01, 0x39
			0x39, 0x01, 0x00, 0x00, 0x0a, 0x00, 0x03, 0x51, 0x00, 0x00
			0x05, 0x01, 0x00, 0x00, 0x0a, 0x00, 0x01, 0x29"</PanelAodEnterCommand>

	<PanelAodLevel1BlCommand>"0x39, 0x01, 0x00, 0x00, 0x0a, 0x00, 0x03, 0x51, 0x01, 0xFF"</PanelAodLevel1BlCommand>

	<PanelAodLevel2BlCommand>"0x39, 0x01, 0x00, 0x00, 0x0a, 0x00, 0x03, 0x51, 0x04, 0xFF"</PanelAodLevel2BlCommand>

	<PanelAodLevel3BlCommand>"0x39, 0x01, 0x00, 0x00, 0x0a, 0x00, 0x03, 0x51, 0x07, 0xFF"</PanelAodLevel3BlCommand>

	<PanelAodExitCommand>"0x05, 0x01, 0x00, 0x00, 0x0a, 0x00, 0x01, 0x28
			0x05, 0x01, 0x00, 0x00, 0x0a, 0x00, 0x01, 0x38
			0x39, 0x01, 0x00, 0x00, 0x0a, 0x00, 0x03, 0x51, 0x00, 0x00
			0x05, 0x01, 0x00, 0x00, 0x0a, 0x00, 0x01, 0x29"</PanelAodExitCommand>

	<PanelVersion>"V3,V4,VN1,VN2"</PanelVersion>
	<PanelVersionCommand>"0x06, 0x01, 0x00, 0x00, 0x0a, 0x00, 0x0E, 0xB1, 0x0D, 0x00, 0x00, 0x00, 0x00, 0x00, 0x00, 0x00, 0x00, 0x00, 0x00, 0x00, 0x00"</PanelVersionCommand>
	<PanelSecendVersionEnterCommand>"0x15, 0x01, 0x00, 0x00, 0x0a, 0x00, 0x02, 0xB0, 0x66"</PanelSecendVersionEnterCommand>
	<PanelSecendVersionCommand>"0x06, 0x01, 0x00, 0x00, 0x0a, 0x00, 0x02, 0xCF, 0x01"</PanelSecendVersionCommand>
	<PanelVersionValue>"0xAD, 0x00
			0x96, 0x00
			0xCA, 0x00
			0xCA, 0x07"</PanelVersionValue>

	<!-- Grayscale Optimize Command-->
	<PanelGrayscaleOptimizeCommand>"0x39, 0x01, 0x00, 0x00, 0x0a, 0x00, 0x08, 0x57, 0x00, 0x20, 0x01, 0xF8, 0xDF, 0xF0, 0x00"</PanelGrayscaleOptimizeCommand>

	<!-- TpColor Command-->
	<PanelTpColorCommand>"0x06, 0x01, 0x00, 0x00, 0x0a, 0x00, 0x17, 0xC1, 0x16, 0x00, 0x00, 0x00, 0x00, 0x00, 0x00, 0x00, 0x00, 0x00, 0x00, 0x00, 0x00, 0x00, 0x00, 0x00, 0x00, 0x00, 0x00, 0x00, 0x00, 0x00"</PanelTpColorCommand>

	<!-- Panel CE Command -->
	<PanelCeOffMode>""</PanelCeOffMode>
	<PanelCeSrgbMode>""</PanelCeSrgbMode>
	<PanelCeUserMode>""</PanelCeUserMode>
	<PanelCeVividMode>""</PanelCeVividMode>

	<!-- for esd check -->
	<PanelEsdRegCommand>"0x15, 0x01, 0x00, 0x00, 0x0a, 0x00, 0x02, 0x02, 0x01
			0x06, 0x01, 0x00, 0x00, 0x0a, 0x00, 0x01, 0x0a"</PanelEsdRegCommand>
	<PanelEsdValue>"0x9c"</PanelEsdValue>

	<!-- for mipi tr check -->
	<PanelCheckRegCommand>"0x06, 0x01, 0x00, 0x00, 0x0a, 0x00, 0x01, 0x0a"</PanelCheckRegCommand>
	<PanelCheckRegValue>"0xb4"</PanelCheckRegValue>

	<!-- for display region-->
	<PanelDirtyRegionCommand>"0x39, 0x01, 0x00, 0x00, 0x05, 0x00, 0x05, 0x2A, 0x00, 0x00, 0x04, 0xAF
				0x39, 0x01, 0x00, 0x00, 0x05, 0x00, 0x05, 0x2B, 0x00, 0x00, 0x0A, 0x4F"</PanelDirtyRegionCommand>

	<!-- 2d barcode support -->
	<Barcode2DCommand>"0x06, 0x01, 0x00, 0x00, 0x20, 0x00, 0x15, 0xC1, 0x00, 0x00, 0x00, 0x00, 0x00, 0x00, 0x00, 0x00, 0x00, 0x00, 0x00, 0x00, 0x00, 0x00, 0x00, 0x00, 0x00, 0x00, 0x00, 0x00"</Barcode2DCommand>

	<!-- for checksum -->
	<PanelChecksumEnableCommand>"0x39, 0x01, 0x00, 0x00, 0x0a, 0x00, 0x03, 0x7F, 0x5A, 0x5A
			0x39, 0x01, 0x00, 0x00, 0x0a, 0x00, 0x03, 0xF0, 0x5A, 0x5A
			0x39, 0x01, 0x00, 0x00, 0x0a, 0x00, 0x03, 0xF1, 0x5A, 0x5A
			0x39, 0x01, 0x00, 0x00, 0x0a, 0x00, 0x03, 0xF2, 0x5A, 0x5A
			0x39, 0x01, 0x00, 0x00, 0x0a, 0x00, 0x02, 0xB0, 0x0C
			0x39, 0x01, 0x00, 0x00, 0x0a, 0x00, 0x02, 0xEE, 0x80"</PanelChecksumEnableCommand>
	<PanelChecksumEnableCommandState>0</PanelChecksumEnableCommandState>
	<PanelChecksumDisableCommand>"0x15, 0x01, 0x00, 0x00, 0x0a, 0x00, 0x02, 0xEE, 0x00"</PanelChecksumDisableCommand>
	<PanelChecksumDisableCommandState>0</PanelChecksumDisableCommandState>
	<PanelChecksumCommand>"0x39, 0x01, 0x00, 0x00, 0x0a, 0x00, 0x02, 0xB0, 0x3A
			0x06, 0x01, 0x00, 0x00, 0x0a, 0x00, 0x08, 0xDD, 0x00, 0x00, 0x00, 0x00, 0x00, 0x00, 0x00"</PanelChecksumCommand>
	<PanelChecksumValue>"0x18, 0xb9, 0x47, 0xe6, 0x18, 0xb9, 0x47, 0xe6
			0x13, 0xa5, 0x67, 0x1e, 0x13, 0xa5, 0x67, 0x1e
			0x18, 0x4e, 0x1c, 0xa9, 0x18, 0x4e, 0x1c, 0xa9"</PanelChecksumValue>
	<PanelChecksumCommandState>0</PanelChecksumCommandState>
	<PanelLogoChecksumValue>"0x23, 0x8c, 0x40, 0x30, 0x0A, 0x55, 0x90, 0xAC"</PanelLogoChecksumValue>
	<!-- for pcd check -->
	<PanelStartPcdCheckCommand>"0x39, 0x01, 0x00, 0x00, 0x0a, 0x00, 0x03, 0x7F, 0x5A, 0x5A
			0x39, 0x01, 0x00, 0x00, 0x0a, 0x00, 0x03, 0xF0, 0x5A, 0x5A
			0x39, 0x01, 0x00, 0x00, 0x0a, 0x00, 0x03, 0xF1, 0x5A, 0x5A
			0x39, 0x01, 0x00, 0x00, 0x0a, 0x00, 0x03, 0xF2, 0x5A, 0x5A
			0x39, 0x01, 0x00, 0x00, 0x0a, 0x00, 0x02, 0xB0, 0x13
			0x39, 0x01, 0x00, 0x00, 0x32, 0x01, 0x03, 0xE2, 0xF1, 0x00
			0x39, 0x01, 0x00, 0x00, 0x0a, 0x00, 0x02, 0xB0, 0x15
			0x39, 0x01, 0x00, 0x00, 0x32, 0x01, 0x03, 0xE2, 0x00, 0x00
			0x39, 0x01, 0x00, 0x00, 0x0a, 0x00, 0x02, 0xB0, 0x17
			0x39, 0x01, 0x00, 0x00, 0x0a, 0x00, 0x03, 0xE2, 0x00, 0x00"</PanelStartPcdCheckCommand>
	<PanelSwitchPageCommand>"0x39, 0x01, 0x00, 0x00, 0x0a, 0x00, 0x03, 0x7F, 0x5A, 0x5A
			0x39, 0x01, 0x00, 0x00, 0x0a, 0x00, 0x03, 0xF0, 0x5A, 0x5A
			0x39, 0x01, 0x00, 0x00, 0x0a, 0x00, 0x03, 0xF1, 0x5A, 0x5A
			0x39, 0x01, 0x00, 0x00, 0x0a, 0x00, 0x03, 0xF2, 0x5A, 0x5A
			0x39, 0x01, 0x00, 0x00, 0x0a, 0x00, 0x02, 0xB0, 0x70"</PanelSwitchPageCommand>
	<PanelSwitchPageCommandState>0</PanelSwitchPageCommandState>
	<PanelPcdCheckRegCommand>"0x06, 0x01, 0x00, 0x00, 0x0a, 0x00, 0x01, 0xDD"</PanelPcdCheckRegCommand>
	<PanelPcdCheckRegCommandState>0</PanelPcdCheckRegCommandState>
	<PanelPcdCheckRegValue>"0x00"</PanelPcdCheckRegValue>

	<!-- color aod detect cmds -->
	<ColorAodDetectEnterCommand>"0x05, 0x01, 0x00, 0x00, 0x0a, 0x00, 0x01, 0x28
			0x05, 0x01, 0x00, 0x00, 0x1e, 0x01, 0x01, 0x39
			0x39, 0x01, 0x00, 0x00, 0x0a, 0x00, 0x03, 0x51, 0x00, 0x00
			0x15, 0x01, 0x00, 0x00, 0x0a, 0x00, 0x02, 0xB0, 0x05
			0x15, 0x01, 0x00, 0x00, 0x0a, 0x00, 0x02, 0xE5, 0x60
			0x15, 0x01, 0x00, 0x00, 0x0a, 0x00, 0x02, 0xB0, 0x08
			0x15, 0x01, 0x00, 0x00, 0x0a, 0x00, 0x02, 0xE5, 0x0D
			0x05, 0x01, 0x00, 0x00, 0x0a, 0x00, 0x01, 0x29
			0x39, 0x01, 0x00, 0x00, 0x0a, 0x00, 0x03, 0x51, 0x01, 0xFF"</ColorAodDetectEnterCommand>
	<ColorAodDetectExitCommand>"0x05, 0x01, 0x00, 0x00, 0x0a, 0x00, 0x01, 0x28
			0x05, 0x01, 0x00, 0x00, 0x14, 0x01, 0x01, 0x38
			0x39, 0x01, 0x00, 0x00, 0x0a, 0x00, 0x03, 0x51, 0x00, 0x00
			0x05, 0x01, 0x00, 0x00, 0x0a, 0x00, 0x01, 0x29"</ColorAodDetectExitCommand>
	<!--vertical line test-->
	<VtcLineCommand>"0x39, 0x01, 0x00, 0x00, 0x0a, 0x00, 0x03, 0x7F, 0x5A, 0x5A
				0x39, 0x01, 0x00, 0x00, 0x0a, 0x00, 0x03, 0xF0, 0x5A, 0x5A
				0x39, 0x01, 0x00, 0x00, 0x0a, 0x00, 0x03, 0xF1, 0x5A, 0x5A
				0x39, 0x01, 0x00, 0x00, 0x0a, 0x00, 0x03, 0xF2, 0x5A, 0x5A
				0x15, 0x01, 0x00, 0x00, 0x0a, 0x00, 0x02, 0x02, 0x01
				0x15, 0x01, 0x00, 0x00, 0x0a, 0x00, 0x02, 0x59, 0x00
				0x39, 0x01, 0x00, 0x00, 0x0a, 0x00, 0x05, 0x2A, 0x00, 0x00, 0x05, 0x3F
				0x39, 0x01, 0x00, 0x00, 0x0a, 0x00, 0x05, 0x2B, 0x00, 0x00, 0x0A, 0xD3
				0x39, 0x01, 0x00, 0x00, 0x0a, 0x00, 0x03, 0x51, 0x00, 0x00
				0x15, 0x01, 0x00, 0x00, 0x0a, 0x00, 0x02, 0x53, 0x20
				0x39, 0x01, 0x00, 0x00, 0x0a, 0x00, 0x08, 0x57, 0x00, 0x00, 0x01, 0xF8, 0xFF, 0xF0, 0x00
				0x39, 0x01, 0x00, 0x00, 0x0a, 0x00, 0x07, 0x58, 0x00, 0x00, 0x01, 0xF8, 0xFF, 0xF0
				0x15, 0x01, 0x00, 0x00, 0x0a, 0x00, 0x02, 0x76, 0x00
				0x15, 0x01, 0x00, 0x00, 0x0a, 0x00, 0x02, 0x35, 0x00
				0x05, 0x01, 0x00, 0x00, 0x78, 0x01, 0x01, 0x11
				0x39, 0x01, 0x00, 0x00, 0x14, 0x01, 0x0C, 0xE1, 0x54, 0x0A, 0xD4, 0x00, 0x60, 0x00, 0x60, 0x18, 0x00, 0x05, 0xac
				0x39, 0x01, 0x00, 0x00, 0x0a, 0x00, 0x03, 0x7F, 0x5A, 0x5A
				0x39, 0x01, 0x00, 0x00, 0x0a, 0x00, 0x03, 0xF0, 0x5A, 0x5A
				0x39, 0x01, 0x00, 0x00, 0x0a, 0x00, 0x03, 0xF1, 0x5A, 0x5A
				0x39, 0x01, 0x00, 0x00, 0x0a, 0x00, 0x03, 0xF2, 0x5A, 0x5A
				0x39, 0x01, 0x00, 0x00, 0x0a, 0x00, 0x03, 0xE2, 0x03, 0x0E
				0x15, 0x01, 0x00, 0x00, 0x0a, 0x00, 0x02, 0xB0, 0x48
				0x39, 0x01, 0x00, 0x00, 0x0a, 0x00, 0x04, 0xE2, 0x1F, 0x3F, 0x3F
				0x39, 0x01, 0x00, 0x00, 0x0a, 0x00, 0x03, 0x7F, 0x5A, 0x5A
				0x39, 0x01, 0x00, 0x00, 0x0a, 0x00, 0x03, 0xF0, 0x5A, 0x5A
				0x39, 0x01, 0x00, 0x00, 0x0a, 0x00, 0x03, 0xF1, 0x5A, 0x5A
				0x39, 0x01, 0x00, 0x00, 0x0a, 0x00, 0x03, 0xF2, 0x5A, 0x5A
				0x15, 0x01, 0x00, 0x00, 0x0a, 0x00, 0x02, 0xB0, 0x2B
				0x39, 0x01, 0x00, 0x00, 0x0a, 0x00, 0x09, 0xB1, 0x70, 0x32, 0x11, 0x11, 0x10, 0x00, 0xFF, 0x01
				0x39, 0x01, 0x00, 0x00, 0x0a, 0x00, 0x29, 0xB4, 0x00, 0xFF, 0x00, 0x00, 0x00, 0x00, 0xB4, 0xA0, 0x84, 0x9B, 0x96, 0x9A, 0xB2, 0x38, 0xFF, 0x00, 0x00, 0x00, 0x00, 0xB7, 0xA1, 0x7E, 0x91, 0x86, 0x92, 0xC3, 0x45, 0xFF, 0x00, 0x00, 0x00, 0x00, 0xB0, 0xA0, 0x87, 0x9C, 0x8C, 0x88, 0xB7, 0x53
				0x0A, 0x01, 0x00, 0x00, 0x01, 0x01, 0x80, 0x11, 0x00, 0x00, 0x89, 0x30, 0x80, 0x0A, 0xD4, 0x05, 0x40, 0x00, 0x24, 0x02, 0xA0, 0x02, 0xA0, 0x02, 0x00, 0x02, 0x50, 0x00, 0x20, 0x03, 0xDB, 0x00, 0x09, 0x00, 0x0C, 0x02, 0xBF, 0x02, 0x46, 0x18, 0x00, 0x10, 0xF0, 0x03, 0x0C, 0x20, 0x00, 0x06, 0x0B, 0x0B, 0x33, 0x0E, 0x1C, 0x2A, 0x38, 0x46, 0x54, 0x62, 0x69, 0x70, 0x77, 0x79, 0x7B, 0x7D, 0x7E, 0x01, 0x02, 0x01, 0x00, 0x09, 0x40, 0x09, 0xBE, 0x19, 0xFC, 0x19, 0xFA, 0x19, 0xF8, 0x1A, 0x38, 0x1A, 0x78, 0x1A, 0xB6, 0x2A, 0xF6, 0x2B, 0x34, 0x2B, 0x74, 0x3B, 0x74, 0x6B, 0xF4, 0x00, 0x00, 0x00, 0x00, 0x00, 0x00, 0x00, 0x00, 0x00, 0x00, 0x00, 0x00, 0x00, 0x00, 0x00, 0x00, 0x00, 0x00, 0x00, 0x00, 0x00, 0x00, 0x00, 0x00, 0x00, 0x00, 0x00, 0x00, 0x00, 0x00, 0x00, 0x00, 0x00, 0x00, 0x00, 0x00, 0x00, 0x00, 0x00, 0x00
				0x15, 0x01, 0x00, 0x00, 0x0a, 0x00, 0x02, 0xB0, 0xE9
				0x39, 0x01, 0x00, 0x00, 0x0a, 0x00, 0x0D, 0xC0, 0x60, 0x80, 0x60, 0x70, 0x80, 0x70, 0x80, 0x60, 0x80, 0x80, 0x60, 0x80
				0x39, 0x01, 0x00, 0x00, 0x0a, 0x00, 0x05, 0xE5, 0x00, 0xA4, 0x0A, 0xF0
				0x39, 0x01, 0x00, 0x00, 0x0a, 0x00, 0x03, 0x44, 0x00, 0x04
				0x39, 0x01, 0x00, 0x00, 0x0a, 0x00, 0x03, 0xF0, 0xA5, 0xA5
				0x39, 0x01, 0x00, 0x00, 0x0a, 0x00, 0x03, 0xF1, 0xA5, 0xA5
				0x39, 0x01, 0x00, 0x00, 0x0a, 0x00, 0x03, 0xF2, 0xA5, 0xA5
				0x05, 0x01, 0x00, 0x00, 0x0a, 0x00, 0x01, 0x29"</VtcLineCommand>
	<VtcLineCommandState>0</VtcLineCommandState>
	<HorLineCommand>"0x39, 0x01, 0x00, 0x00, 0x0a, 0x00, 0x03, 0x7F, 0x5A, 0x5A
				0x39, 0x01, 0x00, 0x00, 0x0a, 0x00, 0x03, 0xF0, 0x5A, 0x5A
				0x39, 0x01, 0x00, 0x00, 0x0a, 0x00, 0x03, 0xF1, 0x5A, 0x5A
				0x39, 0x01, 0x00, 0x00, 0x0a, 0x00, 0x03, 0xF2, 0x5A, 0x5A
				0x15, 0x01, 0x00, 0x00, 0x0a, 0x00, 0x02, 0x02, 0x01
				0x15, 0x01, 0x00, 0x00, 0x0a, 0x00, 0x02, 0x59, 0x00
				0x39, 0x01, 0x00, 0x00, 0x0a, 0x00, 0x05, 0x2A, 0x00, 0x00, 0x05, 0x3F
				0x39, 0x01, 0x00, 0x00, 0x0a, 0x00, 0x05, 0x2B, 0x00, 0x00, 0x0A, 0xD3
				0x39, 0x01, 0x00, 0x00, 0x0a, 0x00, 0x03, 0x51, 0x00, 0x00
				0x15, 0x01, 0x00, 0x00, 0x0a, 0x00, 0x02, 0x53, 0x20
				0x39, 0x01, 0x00, 0x00, 0x0a, 0x00, 0x08, 0x57, 0x00, 0x00, 0x01, 0xF8, 0xFF, 0xF0, 0x00
				0x39, 0x01, 0x00, 0x00, 0x0a, 0x00, 0x07, 0x58, 0x00, 0x00, 0x01, 0xF8, 0xFF, 0xF0
				0x15, 0x01, 0x00, 0x00, 0x0a, 0x00, 0x02, 0x76, 0x00
				0x15, 0x01, 0x00, 0x00, 0x0a, 0x00, 0x02, 0x35, 0x00
				0x05, 0x01, 0x00, 0x00, 0x78, 0x01, 0x01, 0x11
				0x39, 0x01, 0x00, 0x00, 0x14, 0x01, 0x0C, 0xE1, 0x54, 0x0A, 0xD4, 0x00, 0x60, 0x00, 0x60, 0x18, 0x00, 0x00, 0x12
				0x39, 0x01, 0x00, 0x00, 0x0a, 0x00, 0x03, 0x7F, 0x5A, 0x5A
				0x39, 0x01, 0x00, 0x00, 0x0a, 0x00, 0x03, 0xF0, 0x5A, 0x5A
				0x39, 0x01, 0x00, 0x00, 0x0a, 0x00, 0x03, 0xF1, 0x5A, 0x5A
				0x39, 0x01, 0x00, 0x00, 0x0a, 0x00, 0x03, 0xF2, 0x5A, 0x5A
				0x39, 0x01, 0x00, 0x00, 0x0a, 0x00, 0x03, 0xE2, 0x03, 0x0E
				0x15, 0x01, 0x00, 0x00, 0x0a, 0x00, 0x02, 0xB0, 0x48
				0x39, 0x01, 0x00, 0x00, 0x0a, 0x00, 0x04, 0xE2, 0x1F, 0x3F, 0x3F
				0x39, 0x01, 0x00, 0x00, 0x0a, 0x00, 0x03, 0x7F, 0x5A, 0x5A
				0x39, 0x01, 0x00, 0x00, 0x0a, 0x00, 0x03, 0xF0, 0x5A, 0x5A
				0x39, 0x01, 0x00, 0x00, 0x0a, 0x00, 0x03, 0xF1, 0x5A, 0x5A
				0x39, 0x01, 0x00, 0x00, 0x0a, 0x00, 0x03, 0xF2, 0x5A, 0x5A
				0x15, 0x01, 0x00, 0x00, 0x0a, 0x00, 0x02, 0xB0, 0xD4
				0x39, 0x01, 0x00, 0x00, 0x0a, 0x00, 0x25, 0xD6, 0x56, 0xD6, 0x16, 0xD6, 0x16, 0x96, 0x96, 0x96, 0x16, 0x16, 0x16, 0x16, 0x16, 0x96, 0x96, 0x96, 0x96, 0x96, 0x16, 0x16, 0x16, 0x16, 0x16, 0x16, 0x16, 0x16, 0x16, 0x16, 0x16, 0x16, 0x16, 0x16, 0x16, 0x16, 0x16, 0x16
				0x0A, 0x01, 0x00, 0x00, 0x01, 0x01, 0x80, 0x11, 0x00, 0x00, 0x89, 0x30, 0x80, 0x0A, 0xD4, 0x05, 0x40, 0x00, 0x24, 0x02, 0xA0, 0x02, 0xA0, 0x02, 0x00, 0x02, 0x50, 0x00, 0x20, 0x03, 0xDB, 0x00, 0x09, 0x00, 0x0C, 0x02, 0xBF, 0x02, 0x46, 0x18, 0x00, 0x10, 0xF0, 0x03, 0x0C, 0x20, 0x00, 0x06, 0x0B, 0x0B, 0x33, 0x0E, 0x1C, 0x2A, 0x38, 0x46, 0x54, 0x62, 0x69, 0x70, 0x77, 0x79, 0x7B, 0x7D, 0x7E, 0x01, 0x02, 0x01, 0x00, 0x09, 0x40, 0x09, 0xBE, 0x19, 0xFC, 0x19, 0xFA, 0x19, 0xF8, 0x1A, 0x38, 0x1A, 0x78, 0x1A, 0xB6, 0x2A, 0xF6, 0x2B, 0x34, 0x2B, 0x74, 0x3B, 0x74, 0x6B, 0xF4, 0x00, 0x00, 0x00, 0x00, 0x00, 0x00, 0x00, 0x00, 0x00, 0x00, 0x00, 0x00, 0x00, 0x00, 0x00, 0x00, 0x00, 0x00, 0x00, 0x00, 0x00, 0x00, 0x00, 0x00, 0x00, 0x00, 0x00, 0x00, 0x00, 0x00, 0x00, 0x00, 0x00, 0x00, 0x00, 0x00, 0x00, 0x00, 0x00, 0x00
				0x15, 0x01, 0x00, 0x00, 0x0a, 0x00, 0x02, 0xB0, 0xE9
				0x39, 0x01, 0x00, 0x00, 0x0a, 0x00, 0x0D, 0xC0, 0x60, 0x80, 0x60, 0x70, 0x80, 0x70, 0x80, 0x60, 0x80, 0x80, 0x60, 0x80
				0x39, 0x01, 0x00, 0x00, 0x0a, 0x00, 0x05, 0xE5, 0x00, 0xA4, 0x0A, 0xF0
				0x39, 0x01, 0x00, 0x00, 0x0a, 0x00, 0x03, 0x44, 0x00, 0x04
				0x39, 0x01, 0x00, 0x00, 0x0a, 0x00, 0x03, 0xF0, 0xA5, 0xA5
				0x39, 0x01, 0x00, 0x00, 0x0a, 0x00, 0x03, 0xF1, 0xA5, 0xA5
				0x39, 0x01, 0x00, 0x00, 0x0a, 0x00, 0x03, 0xF2, 0xA5, 0xA5
				0x05, 0x01, 0x00, 0x00, 0x0a, 0x00, 0x01, 0x29"</HorLineCommand>
	<HorLineCommandState>0</HorLineCommandState>
	<!--ddic low voltage detect test-->
	<DdicLVDetectEnter1Command>"0x39, 0x01, 0x00, 0x00, 0x0a, 0x00, 0x03, 0xF0, 0x5A, 0x5A
				0x39, 0x01, 0x00, 0x00, 0x0a, 0x00, 0x03, 0xF1, 0x5A, 0x5A
				0x39, 0x01, 0x00, 0x00, 0x0a, 0x00, 0x03, 0xF2, 0x5A, 0x5A
				0x39, 0x01, 0x00, 0x00, 0x0a, 0x01, 0x09, 0xF6, 0x08, 0x00, 0x00, 0x00, 0x00, 0x10, 0x00, 0xFC
				0x39, 0x01, 0x00, 0x00, 0x0a, 0x00, 0x02, 0xE8, 0x01
				0x39, 0x01, 0x00, 0x00, 0x0a, 0x00, 0x03, 0xF0, 0xA5, 0xA5
				0x39, 0x01, 0x00, 0x00, 0x0a, 0x00, 0x03, 0xF1, 0xA5, 0xA5
				0x39, 0x01, 0x00, 0x00, 0x0a, 0x00, 0x03, 0xF2, 0xA5, 0xA5"</DdicLVDetectEnter1Command>
	<DdicLVDetectEnter1CommandState>0</DdicLVDetectEnter1CommandState>
	<DdicLVDetectEnter2Command>"0x39, 0x01, 0x00, 0x00, 0x0a, 0x00, 0x03, 0xF0, 0x5A, 0x5A
				0x39, 0x01, 0x00, 0x00, 0x0a, 0x00, 0x03, 0xF1, 0x5A, 0x5A
				0x39, 0x01, 0x00, 0x00, 0x0a, 0x00, 0x03, 0xF2, 0x5A, 0x5A
				0x39, 0x01, 0x00, 0x00, 0x0a, 0x01, 0x09, 0xF6, 0x08, 0x00, 0x00, 0x00, 0x00, 0x10, 0x00, 0xFC
				0x39, 0x01, 0x00, 0x00, 0x0a, 0x00, 0x02, 0xE8, 0x01
				0x39, 0x01, 0x00, 0x00, 0x0a, 0x00, 0x03, 0xF0, 0xA5, 0xA5
				0x39, 0x01, 0x00, 0x00, 0x0a, 0x00, 0x03, 0xF1, 0xA5, 0xA5
				0x39, 0x01, 0x00, 0x00, 0x0a, 0x00, 0x03, 0xF2, 0xA5, 0xA5"</DdicLVDetectEnter2Command>
	<DdicLVDetectEnter2CommandState>0</DdicLVDetectEnter2CommandState>
	<DdicLVDetectEnter3Command>"0x39, 0x01, 0x00, 0x00, 0x0a, 0x00, 0x03, 0xF0, 0x5A, 0x5A
				0x39, 0x01, 0x00, 0x00, 0x0a, 0x00, 0x03, 0xF1, 0x5A, 0x5A
				0x39, 0x01, 0x00, 0x00, 0x0a, 0x00, 0x03, 0xF2, 0x5A, 0x5A
				0x39, 0x01, 0x00, 0x00, 0x0a, 0x01, 0x09, 0xF6, 0x08, 0x00, 0x00, 0x00, 0x00, 0x10, 0x00, 0xFC
				0x39, 0x01, 0x00, 0x00, 0x0a, 0x00, 0x02, 0xE8, 0x01
				0x39, 0x01, 0x00, 0x00, 0x0a, 0x00, 0x03, 0xF0, 0xA5, 0xA5
				0x39, 0x01, 0x00, 0x00, 0x0a, 0x00, 0x03, 0xF1, 0xA5, 0xA5
				0x39, 0x01, 0x00, 0x00, 0x0a, 0x00, 0x03, 0xF2, 0xA5, 0xA5"</DdicLVDetectEnter3Command>
	<DdicLVDetectEnter3CommandState>0</DdicLVDetectEnter3CommandState>
	<DdicLVDetectEnter4Command>"0x39, 0x01, 0x00, 0x00, 0x0a, 0x00, 0x03, 0xF0, 0x5A, 0x5A
				0x39, 0x01, 0x00, 0x00, 0x0a, 0x00, 0x03, 0xF1, 0x5A, 0x5A
				0x39, 0x01, 0x00, 0x00, 0x0a, 0x00, 0x03, 0xF2, 0x5A, 0x5A
				0x39, 0x01, 0x00, 0x00, 0x0a, 0x01, 0x09, 0xF6, 0x08, 0x00, 0x00, 0x00, 0x00, 0x10, 0x00, 0xFC
				0x39, 0x01, 0x00, 0x00, 0x0a, 0x00, 0x02, 0xE8, 0x01
				0x39, 0x01, 0x00, 0x00, 0x0a, 0x00, 0x03, 0xF0, 0xA5, 0xA5
				0x39, 0x01, 0x00, 0x00, 0x0a, 0x00, 0x03, 0xF1, 0xA5, 0xA5
				0x39, 0x01, 0x00, 0x00, 0x0a, 0x00, 0x03, 0xF2, 0xA5, 0xA5"</DdicLVDetectEnter4Command>
	<DdicLVDetectEnter4CommandState>0</DdicLVDetectEnter4CommandState>

	<DdicLVDetectRd1Command>"0x39, 0x01, 0x00, 0x00, 0x0a, 0x00, 0x03, 0xF0, 0x5A, 0x5A
				0x39, 0x01, 0x00, 0x00, 0x0a, 0x00, 0x03, 0xF1, 0x5A, 0x5A
				0x39, 0x01, 0x00, 0x00, 0x0a, 0x00, 0x03, 0xF2, 0x5A, 0x5A
				0x39, 0x01, 0x00, 0x00, 0x0a, 0x00, 0x02, 0xB0, 0x59
				0x06, 0x01, 0x00, 0x00, 0x0a, 0x00, 0x01, 0xDD
				0x39, 0x01, 0x00, 0x00, 0x0a, 0x00, 0x03, 0xF0, 0xA5, 0xA5
				0x39, 0x01, 0x00, 0x00, 0x0a, 0x00, 0x03, 0xF1, 0xA5, 0xA5
				0x39, 0x01, 0x00, 0x00, 0x0a, 0x00, 0x03, 0xF2, 0xA5, 0xA5"</DdicLVDetectRd1Command>
	<DdicLVDetectRd1CommandState>0</DdicLVDetectRd1CommandState>
	<DdicLVDetectRd2Command>"0x39, 0x01, 0x00, 0x00, 0x0a, 0x00, 0x03, 0xF0, 0x5A, 0x5A
				0x39, 0x01, 0x00, 0x00, 0x0a, 0x00, 0x03, 0xF1, 0x5A, 0x5A
				0x39, 0x01, 0x00, 0x00, 0x0a, 0x00, 0x03, 0xF2, 0x5A, 0x5A
				0x39, 0x01, 0x00, 0x00, 0x0a, 0x00, 0x02, 0xB0, 0x59
				0x06, 0x01, 0x00, 0x00, 0x0a, 0x00, 0x01, 0xDD
				0x39, 0x01, 0x00, 0x00, 0x0a, 0x00, 0x03, 0xF0, 0xA5, 0xA5
				0x39, 0x01, 0x00, 0x00, 0x0a, 0x00, 0x03, 0xF1, 0xA5, 0xA5
				0x39, 0x01, 0x00, 0x00, 0x0a, 0x00, 0x03, 0xF2, 0xA5, 0xA5"</DdicLVDetectRd2Command>
	<DdicLVDetectRd2CommandState>0</DdicLVDetectRd2CommandState>
	<DdicLVDetectRd3Command>"0x39, 0x01, 0x00, 0x00, 0x0a, 0x00, 0x03, 0xF0, 0x5A, 0x5A
				0x39, 0x01, 0x00, 0x00, 0x0a, 0x00, 0x03, 0xF1, 0x5A, 0x5A
				0x39, 0x01, 0x00, 0x00, 0x0a, 0x00, 0x03, 0xF2, 0x5A, 0x5A
				0x39, 0x01, 0x00, 0x00, 0x0a, 0x00, 0x02, 0xB0, 0x59
				0x06, 0x01, 0x00, 0x00, 0x0a, 0x00, 0x01, 0xDD
				0x39, 0x01, 0x00, 0x00, 0x0a, 0x00, 0x03, 0xF0, 0xA5, 0xA5
				0x39, 0x01, 0x00, 0x00, 0x0a, 0x00, 0x03, 0xF1, 0xA5, 0xA5
				0x39, 0x01, 0x00, 0x00, 0x0a, 0x00, 0x03, 0xF2, 0xA5, 0xA5"</DdicLVDetectRd3Command>
	<DdicLVDetectRd3CommandState>0</DdicLVDetectRd3CommandState>
	<DdicLVDetectRd4Command>"0x39, 0x01, 0x00, 0x00, 0x0a, 0x00, 0x03, 0xF0, 0x5A, 0x5A
				0x39, 0x01, 0x00, 0x00, 0x0a, 0x00, 0x03, 0xF1, 0x5A, 0x5A
				0x39, 0x01, 0x00, 0x00, 0x0a, 0x00, 0x03, 0xF2, 0x5A, 0x5A
				0x39, 0x01, 0x00, 0x00, 0x0a, 0x00, 0x02, 0xB0, 0x59
				0x06, 0x01, 0x00, 0x00, 0x0a, 0x00, 0x01, 0xDD
				0x39, 0x01, 0x00, 0x00, 0x0a, 0x00, 0x03, 0xF0, 0xA5, 0xA5
				0x39, 0x01, 0x00, 0x00, 0x0a, 0x00, 0x03, 0xF1, 0xA5, 0xA5
				0x39, 0x01, 0x00, 0x00, 0x0a, 0x00, 0x03, 0xF2, 0xA5, 0xA5"</DdicLVDetectRd4Command>
	<DdicLVDetectRd4CommandState>0</DdicLVDetectRd4CommandState>

	<DdicLVDetectValue1>"0x00"</DdicLVDetectValue1>
	<DdicLVDetectValue2>"0x00"</DdicLVDetectValue2>
	<DdicLVDetectValue3>"0x00"</DdicLVDetectValue3>
	<DdicLVDetectValue4>"0x00"</DdicLVDetectValue4>
</PanelEntry>
</hwlcd>
