<hwlcd>
<PanelEntry>
	<PanelCompatible>"boe_sw43103_lion"</PanelCompatible>
	<PanelName>"BOE_SW43103_LION 6.53' CMD TFT 1176 x 2400"</PanelName>
	<!--lcdtype: amoled_2, lcd_1-->
	<PanelType>0x02</PanelType>
	<PanelXres>1176</PanelXres>
	<PanelYres>2400</PanelYres>
	<PanelWidth>73</PanelWidth>
	<PanelHeight>149</PanelHeight>

	<!-- Panel Command information -->
	<PanelOnCommand>"0x39, 0x01, 0x00, 0x00, 0x0a, 0x00, 0x02, 0xB0, 0xA2
			0x39, 0x01, 0x00, 0x00, 0x0a, 0x00, 0x17, 0xB1, 0x12, 0x02, 0x22, 0x11, 0x41, 0x41, 0xF4, 0xF4, 0xC4, 0x05, 0x0B, 0x0B, 0x19, 0x19, 0x19, 0x19, 0xB4, 0x00, 0x03, 0x08, 0x04, 0x19
			0x39, 0x01, 0x00, 0x00, 0x0a, 0x00, 0x09, 0xB2, 0x0A, 0x0A, 0x89, 0x89, 0xC9, 0xC9, 0x0F, 0x0F
			0x39, 0x01, 0x00, 0x00, 0x0a, 0x00, 0x02, 0xB0, 0xA6
			0x15, 0x01, 0x00, 0x00, 0x0a, 0x00, 0x02, 0xF7, 0xAC
			0x39, 0x01, 0x00, 0x00, 0x0a, 0x00, 0x02, 0xB0, 0xA1
			0x39, 0x01, 0x00, 0x00, 0x0a, 0x00, 0x05, 0x2A, 0x00, 0x00, 0x04, 0x97
			0x39, 0x01, 0x00, 0x00, 0x0a, 0x00, 0x05, 0x2B, 0x00, 0x00, 0x09, 0x5F
			0x39, 0x01, 0x00, 0x00, 0x0a, 0x00, 0x08, 0xB1, 0x07, 0x0F, 0x00, 0x00, 0x80, 0x00, 0x00
			0x39, 0x01, 0x00, 0x00, 0x0a, 0x00, 0x06, 0xB2, 0x00, 0x00, 0x00, 0x00, 0x00
			0x39, 0x01, 0x00, 0x00, 0x0a, 0x00, 0x0D, 0xB3, 0x73, 0x3A, 0x00, 0x10, 0x0C, 0x00, 0x10, 0x0C, 0x28, 0x00, 0x14, 0x14
			0x39, 0x01, 0x00, 0x00, 0x0a, 0x00, 0x04, 0xB4, 0x05, 0x14, 0xAF
			0x39, 0x01, 0x00, 0x00, 0x0a, 0x00, 0x0C, 0xB5, 0x50, 0x12, 0x33, 0x00, 0x1A, 0x00, 0xFF, 0x00, 0x00, 0x00, 0x00
			0x39, 0x01, 0x00, 0x00, 0x0a, 0x00, 0x03, 0xB9, 0x00, 0x00
			0x39, 0x01, 0x00, 0x00, 0x0a, 0x00, 0x05, 0xBC, 0x21, 0x05, 0x0A, 0x00
			0x39, 0x01, 0x00, 0x00, 0x0a, 0x00, 0x0A, 0x69, 0x00, 0x00, 0x00, 0x00, 0x00, 0x00, 0x00, 0x00, 0x00
			0x39, 0x01, 0x00, 0x00, 0x0a, 0x00, 0x12, 0xC1, 0x88, 0x48, 0x60, 0x05, 0x00, 0x00, 0x00, 0x2A, 0x31, 0x39, 0x34, 0x0D, 0x36, 0x36, 0x00, 0x00, 0x02
			0x39, 0x01, 0x00, 0x00, 0x0a, 0x00, 0x0A, 0xC2, 0xF3, 0x20, 0x00, 0x00, 0x7D, 0x2F, 0x02, 0xB1, 0x10
			0x39, 0x01, 0x00, 0x00, 0x0a, 0x00, 0x1F, 0xC3, 0X32, 0X32, 0X32, 0X32, 0X32, 0X32, 0X32, 0X32, 0X32, 0X32, 0X32, 0X32, 0X32, 0X32, 0X32, 0X32, 0X32, 0X32, 0X32, 0X32, 0X32, 0X32, 0X32, 0X32, 0X32, 0X32, 0X32, 0X32, 0X32, 0X32
			0x39, 0x01, 0x00, 0x00, 0x0a, 0x00, 0x0D, 0xC4, 0x32, 0x32, 0x34, 0x34, 0x34, 0x34, 0x34, 0x34, 0x34, 0x34, 0x34, 0x34
			0x39, 0x01, 0x00, 0x00, 0x0a, 0x00, 0x03, 0xC5, 0x00, 0x00
			0x39, 0x01, 0x00, 0x00, 0x0a, 0x00, 0x02, 0xB0, 0xA2
			0x39, 0x01, 0x00, 0x00, 0x0a, 0x00, 0x1A, 0xB3, 0x11, 0x02, 0x56, 0x40, 0x04, 0x00, 0x5F, 0x00, 0x5F, 0x10, 0x00, 0x00, 0x10, 0x36, 0x40, 0x08, 0xFF, 0x9B, 0x1F, 0x9B, 0x1F, 0x00, 0x00, 0x00, 0x00
			0x39, 0x01, 0x00, 0x00, 0x0a, 0x00, 0x18, 0xB4, 0x05, 0x05, 0x40, 0x04, 0x04, 0x94, 0x00, 0x94, 0x00, 0x00, 0x00, 0x00, 0x02, 0x31, 0x37, 0x41, 0x08, 0xFF, 0x2C, 0x33, 0x2C, 0x33, 0x00
			0x39, 0x01, 0x00, 0x00, 0x0a, 0x00, 0x12, 0xB6, 0x05, 0x01, 0x00, 0x00, 0x0F, 0xEA, 0x9B, 0x23, 0x00, 0x04, 0x0F, 0xEA, 0x9B, 0x23, 0x00, 0x04, 0x00
			0x39, 0x01, 0x00, 0x00, 0x0a, 0x00, 0x12, 0xB7, 0x30, 0x0F, 0x0F, 0x10, 0x10, 0x00, 0x00, 0x00, 0x00, 0x00, 0x00, 0x02, 0x02, 0x00, 0x00, 0x00, 0x00
			0x39, 0x01, 0x00, 0x00, 0x0a, 0x00, 0x0C, 0xB8, 0x19, 0x00, 0x22, 0x22, 0x22, 0x00, 0x00, 0x00, 0x00, 0x00, 0x00
			0x39, 0x01, 0x00, 0x00, 0x0a, 0x00, 0x10, 0xB9, 0x54, 0x14, 0x4C, 0x44, 0x14, 0x11, 0x22, 0x00, 0x00, 0x00, 0x05, 0x00, 0x08, 0x19, 0x19
			0x39, 0x01, 0x00, 0x00, 0x0a, 0x00, 0x0C, 0xBA, 0x00, 0x00, 0x00, 0x00, 0x00, 0x1E, 0x1E, 0x00, 0x04, 0x04, 0x00
			0x39, 0x01, 0x00, 0x00, 0x0a, 0x00, 0x14, 0xBB, 0x12, 0x21, 0x33, 0x33, 0x32, 0x14, 0x24, 0x44, 0x03, 0x11, 0x11, 0x00, 0x11, 0x12, 0x05, 0x03, 0x11, 0x01, 0x03
			0x39, 0x01, 0x00, 0x00, 0x0a, 0x00, 0x0D, 0xBD, 0x02, 0x02, 0x01, 0x01, 0x09, 0x07, 0x06, 0x00, 0x70, 0x71, 0x77, 0x00
			0x39, 0x01, 0x00, 0x00, 0x0a, 0x00, 0x0D, 0xBE, 0x02, 0x02, 0x01, 0x01, 0x09, 0x07, 0x06, 0x00, 0x70, 0x71, 0x77, 0x00
			0x39, 0x01, 0x00, 0x00, 0x0a, 0x00, 0x02, 0xB0, 0xA3
			0x39, 0x01, 0x00, 0x00, 0x0a, 0x00, 0x0F, 0xB1, 0x32, 0x32, 0xB2, 0x03, 0x00, 0x00, 0x00, 0x46, 0x50, 0x5A, 0x46, 0x50, 0x5A, 0x00
			0x39, 0x01, 0x00, 0x00, 0x0a, 0x00, 0x1A, 0xB2, 0x2A, 0x00, 0x36, 0x00, 0x36, 0x00, 0x36, 0x00, 0x00, 0x00, 0x00, 0x00, 0x00, 0x00, 0x00, 0x00, 0x44, 0x44, 0x44, 0x2A, 0x2A, 0x2A, 0x10, 0x10, 0x10
			0x39, 0x01, 0x00, 0x00, 0x0a, 0x00, 0x09, 0xB3, 0x1F, 0x63, 0x00, 0x00, 0x20, 0x00, 0x00, 0x00
			0x39, 0x01, 0x00, 0x00, 0x0a, 0x00, 0x16, 0xB4, 0x77, 0x46, 0x34, 0x01, 0x00, 0xFF, 0x33, 0x40, 0xB0, 0x48, 0x90, 0x2C, 0xC8, 0x64, 0x00, 0x57, 0x13, 0xFF, 0xFF, 0xFF, 0xFF
			0x39, 0x01, 0x00, 0x00, 0x0a, 0x00, 0x08, 0xB5, 0x00, 0x3C, 0x00, 0x3C, 0x00, 0x3C, 0x10
			0x39, 0x01, 0x00, 0x00, 0x0a, 0x00, 0x1F, 0xB6, 0x20, 0x00, 0x59, 0x20, 0x00, 0x59, 0x20, 0x00, 0x59, 0x11, 0x02, 0x57, 0x01, 0x69, 0xF0, 0x01, 0xFF, 0x5A, 0x02, 0x1D, 0x3C, 0x02, 0x35, 0x24, 0x02, 0x35, 0x24, 0x02, 0x59, 0x00
			0x39, 0x01, 0x00, 0x00, 0x0a, 0x00, 0x13, 0xB7, 0x20, 0x00, 0x58, 0x20, 0x00, 0x58, 0x20, 0x00, 0x58, 0x20, 0x00, 0x58, 0x20, 0x00, 0x58, 0x20, 0x00, 0x58
			0x39, 0x01, 0x00, 0x00, 0x0a, 0x00, 0x10, 0xB8, 0x40, 0x83, 0xFF, 0x2B, 0x5A, 0xD9, 0x06, 0x50, 0x9A, 0xC5, 0x70, 0x78, 0xB1, 0xCA, 0xEF
			0x39, 0x01, 0x00, 0x00, 0x0a, 0x00, 0x10, 0xB9, 0x40, 0x82, 0xFF, 0x2B, 0xF4, 0xD9, 0x06, 0x50, 0x9A, 0xC5, 0x60, 0x78, 0xAF, 0xC9, 0xEF
			0x39, 0x01, 0x00, 0x00, 0x0a, 0x00, 0x10, 0xBA, 0x40, 0x83, 0xFF, 0x2B, 0xAA, 0xD9, 0x06, 0x90, 0xC2, 0xDA, 0x85, 0x90, 0xBA, 0xCA, 0xEF
			0x39, 0x01, 0x00, 0x00, 0x0a, 0x00, 0x10, 0xBB, 0x40, 0x83, 0xFF, 0x2B, 0x5A, 0xD9, 0x06, 0x50, 0x9A, 0xC5, 0x70, 0x78, 0xB1, 0xCA, 0xEF
			0x39, 0x01, 0x00, 0x00, 0x0a, 0x00, 0x10, 0xBC, 0x40, 0x82, 0xFF, 0x2B, 0xF4, 0xD9, 0x06, 0x50, 0x9A, 0xC5, 0x60, 0x78, 0xAF, 0xC9, 0xEF
			0x39, 0x01, 0x00, 0x00, 0x0a, 0x00, 0x10, 0xBD, 0x40, 0x83, 0xFF, 0x2B, 0xAA, 0xD9, 0x06, 0x90, 0xC2, 0xDA, 0x85, 0x90, 0xBA, 0xCA, 0xEF
			0x39, 0x01, 0x00, 0x00, 0x0a, 0x00, 0x10, 0xBE, 0x40, 0x83, 0xFF, 0x2B, 0x5A, 0xD9, 0x06, 0x50, 0x9A, 0xC5, 0x70, 0x78, 0xB1, 0xCA, 0xEF
			0x39, 0x01, 0x00, 0x00, 0x0a, 0x00, 0x10, 0xBF, 0x40, 0x82, 0xFF, 0x2B, 0xF4, 0xD9, 0x06, 0x50, 0x9A, 0xC5, 0x60, 0x78, 0xAF, 0xC9, 0xEF
			0x39, 0x01, 0x00, 0x00, 0x0a, 0x00, 0x10, 0xC0, 0x40, 0x83, 0xFF, 0x2B, 0xAA, 0xD9, 0x06, 0x90, 0xC2, 0xDA, 0x85, 0x90, 0xBA, 0xCA, 0xEF
			0x39, 0x01, 0x00, 0x00, 0x0a, 0x00, 0x10, 0xC1, 0x40, 0x83, 0xFF, 0x2B, 0x5A, 0xD9, 0x06, 0x50, 0x9A, 0xC5, 0x70, 0x78, 0xB1, 0xCA, 0xEF
			0x39, 0x01, 0x00, 0x00, 0x0a, 0x00, 0x10, 0xC2, 0x40, 0x82, 0xFF, 0x2B, 0xF4, 0xD9, 0x06, 0x50, 0x9A, 0xC5, 0x60, 0x78, 0xAF, 0xC9, 0xEF
			0x39, 0x01, 0x00, 0x00, 0x0a, 0x00, 0x10, 0xC3, 0x40, 0x83, 0xFF, 0x2B, 0xAA, 0xD9, 0x06, 0x90, 0xC2, 0xDA, 0x85, 0x90, 0xBA, 0xCA, 0xEF
			0x39, 0x01, 0x00, 0x00, 0x0a, 0x00, 0x10, 0xC4, 0x40, 0x83, 0xFF, 0x2B, 0x5A, 0xD9, 0x06, 0x50, 0x9A, 0xC5, 0x70, 0x78, 0xB1, 0xCA, 0xEF
			0x39, 0x01, 0x00, 0x00, 0x0a, 0x00, 0x10, 0xC5, 0x40, 0x82, 0xFF, 0x2B, 0xF4, 0xD9, 0x06, 0x50, 0x9A, 0xC5, 0x60, 0x78, 0xAF, 0xC9, 0xEF
			0x39, 0x01, 0x00, 0x00, 0x0a, 0x00, 0x10, 0xC6, 0x40, 0x83, 0xFF, 0x2B, 0xAA, 0xD9, 0x06, 0x90, 0xC2, 0xDA, 0x85, 0x90, 0xBA, 0xCA, 0xEF
			0x39, 0x01, 0x00, 0x00, 0x0a, 0x00, 0x10, 0xC7, 0x40, 0x83, 0xFF, 0x2B, 0x5A, 0xD9, 0x06, 0x50, 0x9A, 0xC5, 0x70, 0x78, 0xB1, 0xCA, 0xEF
			0x39, 0x01, 0x00, 0x00, 0x0a, 0x00, 0x10, 0xC8, 0x40, 0x82, 0xFF, 0x2B, 0xF4, 0xD9, 0x06, 0x50, 0x9A, 0xC5, 0x60, 0x78, 0xAF, 0xC9, 0xEF
			0x39, 0x01, 0x00, 0x00, 0x0a, 0x00, 0x10, 0xC9, 0x40, 0x83, 0xFF, 0x2B, 0xAA, 0xD9, 0x06, 0x90, 0xC2, 0xDA, 0x85, 0x90, 0xBA, 0xCA, 0xEF
			0x39, 0x01, 0x00, 0x00, 0x0a, 0x00, 0x10, 0xCA, 0x40, 0x83, 0xFF, 0x2B, 0x5A, 0xD9, 0x06, 0x50, 0x9A, 0xC5, 0x70, 0x78, 0xB1, 0xCA, 0xEF
			0x39, 0x01, 0x00, 0x00, 0x0a, 0x00, 0x10, 0xCB, 0x40, 0x82, 0xFF, 0x2B, 0xF4, 0xD9, 0x06, 0x50, 0x9A, 0xC5, 0x60, 0x78, 0xAF, 0xC9, 0xEF
			0x39, 0x01, 0x00, 0x00, 0x0a, 0x00, 0x10, 0xCC, 0x40, 0x83, 0xFF, 0x2B, 0xAA, 0xD9, 0x06, 0x90, 0xC2, 0xDA, 0x85, 0x90, 0xBA, 0xCA, 0xEF
			0x39, 0x01, 0x00, 0x00, 0x0a, 0x00, 0x10, 0xCD, 0x40, 0x83, 0xFF, 0x2B, 0x5A, 0xD9, 0x06, 0x50, 0x9A, 0xC5, 0x70, 0x78, 0xB1, 0xCA, 0xEF
			0x39, 0x01, 0x00, 0x00, 0x0a, 0x00, 0x10, 0xCE, 0x40, 0x82, 0xFF, 0x2B, 0xF4, 0xD9, 0x06, 0x50, 0x9A, 0xC5, 0x60, 0x78, 0xAF, 0xC9, 0xEF
			0x39, 0x01, 0x00, 0x00, 0x0a, 0x00, 0x10, 0xCF, 0x40, 0x83, 0xFF, 0x2B, 0xAA, 0xD9, 0x06, 0x90, 0xC2, 0xDA, 0x85, 0x90, 0xBA, 0xCA, 0xEF
			0x39, 0x01, 0x00, 0x00, 0x0a, 0x00, 0x10, 0xD0, 0x40, 0x83, 0xFF, 0x2B, 0x5A, 0xD9, 0x06, 0x50, 0x9A, 0xC5, 0x70, 0x78, 0xB1, 0xCA, 0xEF
			0x39, 0x01, 0x00, 0x00, 0x0a, 0x00, 0x10, 0xD1, 0x40, 0x82, 0xFF, 0x2B, 0xF4, 0xD9, 0x06, 0x50, 0x9A, 0xC5, 0x60, 0x78, 0xAF, 0xC9, 0xEF
			0x39, 0x01, 0x00, 0x00, 0x0a, 0x00, 0x10, 0xD2, 0x40, 0x83, 0xFF, 0x2B, 0xAA, 0xD9, 0x06, 0x90, 0xC2, 0xDA, 0x85, 0x90, 0xBA, 0xCA, 0xEF
			0x39, 0x01, 0x00, 0x00, 0x0a, 0x00, 0x10, 0xD3, 0x40, 0x83, 0xFF, 0x2B, 0x5A, 0xD9, 0x06, 0x50, 0x9A, 0xC5, 0x70, 0x78, 0xB1, 0xCA, 0xEF
			0x39, 0x01, 0x00, 0x00, 0x0a, 0x00, 0x10, 0xD4, 0x40, 0x82, 0xFF, 0x2B, 0xF4, 0xD9, 0x06, 0x50, 0x9A, 0xC5, 0x60, 0x78, 0xAF, 0xC9, 0xEF
			0x39, 0x01, 0x00, 0x00, 0x0a, 0x00, 0x10, 0xD5, 0x40, 0x83, 0xFF, 0x2B, 0xAA, 0xD9, 0x06, 0x90, 0xC2, 0xDA, 0x85, 0x90, 0xBA, 0xCA, 0xEF
			0x39, 0x01, 0x00, 0x00, 0x0a, 0x00, 0x02, 0xB0, 0xA4
			0x39, 0x01, 0x00, 0x00, 0x0a, 0x00, 0x02, 0xB0, 0xA5
			0x39, 0x01, 0x00, 0x00, 0x0a, 0x00, 0x02, 0xC0, 0x00
			0x39, 0x01, 0x00, 0x00, 0x0a, 0x00, 0x02, 0xC8, 0x41
			0x39, 0x01, 0x00, 0x00, 0x0a, 0x00, 0x03, 0xD3, 0x10, 0x06
			0x39, 0x01, 0x00, 0x00, 0x0a, 0x00, 0x02, 0xB0, 0xA6
			0x39, 0x01, 0x00, 0x00, 0x0a, 0x00, 0x18, 0xF2, 0x00, 0x13, 0x00, 0x00, 0x10, 0x00, 0x00, 0x00, 0x00, 0x00, 0x10, 0x90, 0x90, 0x00, 0x00, 0x00, 0x00, 0x00, 0x1F, 0x0F, 0x00, 0x00, 0x00
			0x39, 0x01, 0x00, 0x00, 0x0a, 0x00, 0x05, 0xFC, 0x00, 0x00, 0x01, 0x01
			0x39, 0x01, 0x00, 0x00, 0x0a, 0x00, 0x02, 0xB0, 0xA1
			0x39, 0x01, 0x00, 0x00, 0x0a, 0x00, 0x02, 0x53, 0x00
			0x39, 0x01, 0x00, 0x00, 0x0a, 0x00, 0x02, 0x55, 0x00
			0x39, 0x01, 0x00, 0x00, 0x0a, 0x00, 0x02, 0x3D, 0x00
			0x05, 0x01, 0x00, 0x00, 0x0a, 0x00, 0x01, 0x35
			0x39, 0x01, 0x00, 0x00, 0x0a, 0x00, 0x05, 0x30, 0x00, 0x00, 0x09, 0x5F
			0x39, 0x01, 0x00, 0x00, 0x0a, 0x00, 0x05, 0x31, 0x00, 0x00, 0x04, 0x97
			0x39, 0x01, 0x00, 0x00, 0x0a, 0x00, 0x81, 0xB6, 0x11, 0x00, 0x00, 0x89, 0x30, 0x80, 0x09, 0x60, 0x04, 0x98, 0x00, 0x04, 0x02, 0x4C, 0x02, 0x4C, 0x02, 0x00, 0x02, 0x26, 0x00, 0x20, 0x00, 0x59, 0x00, 0x08, 0x00, 0x0C, 0x20, 0x00, 0x17, 0x59, 0x18, 0x00, 0x10, 0xF0, 0x03, 0x0C, 0x20, 0x00, 0x06, 0x0B, 0x0B, 0x33, 0x0E, 0x1C, 0x2A, 0x38, 0x46, 0x54, 0x62, 0x69, 0x70, 0x77, 0x79, 0x7B, 0x7D, 0x7E, 0x01, 0x02, 0x01, 0x00, 0x09, 0x40, 0x09, 0xBE, 0x19, 0xFC, 0x19, 0xFA, 0x19, 0xF8, 0x1A, 0x38, 0x1A, 0x78, 0x1A, 0xB6, 0x2A, 0xF6, 0x2B, 0x34, 0x2B, 0x74, 0x3B, 0x74, 0x6B, 0xF4, 0x00, 0x00, 0x00, 0x00, 0x00, 0x00, 0x00, 0x00, 0x00, 0x00, 0x00, 0x00, 0x00, 0x00, 0x00, 0x00, 0x00, 0x00, 0x00, 0x00, 0x00, 0x00, 0x00, 0x00, 0x00, 0x00, 0x00, 0x00, 0x00, 0x00, 0x00, 0x00, 0x00, 0x00, 0x00, 0x00, 0x00, 0x00, 0x00, 0x00
			0x39, 0x01, 0x00, 0x00, 0x0a, 0x00, 0x02, 0xB0, 0xCA
			0x39, 0x01, 0x00, 0x00, 0x0a, 0x00, 0x03, 0x51, 0x00, 0x00
			0x05, 0x01, 0x00, 0x00, 0x78, 0x01, 0x01, 0x11
			0x39, 0x01, 0x00, 0x00, 0x14, 0x01, 0x01, 0x29"</PanelOnCommand>

	<PanelOffCommand>"0x05, 0x01, 0x00, 0x00, 0x14, 0x01, 0x01, 0x28
			0x05, 0x01, 0x00, 0x00, 0x55, 0x01, 0x01, 0x10"</PanelOffCommand>

	<PanelBacklightCommand>"0x39, 0x01, 0x00, 0x00, 0x00, 0x00, 0x03, 0x51, 0x00, 0x00"</PanelBacklightCommand>

	<!-- Panel Hbm cmd -->
	<PanelHbmEnterCommand>"0x39, 0x01, 0x00, 0x00, 0x0a, 0x00, 0x03, 0x51, 0x07, 0xFF"</PanelHbmEnterCommand>

	<PanelHbmCommand>"0x39, 0x01, 0x00, 0x00, 0x0a, 0x00, 0x03, 0x51, 0x00, 0x00"</PanelHbmCommand>

	<PanelHbmExitCommand>"0x39, 0x01, 0x00, 0x00, 0x0a, 0x00, 0x03, 0x51, 0x06, 0xF4"</PanelHbmExitCommand>

	<!-- Panel Acl cmd -->
	<PanelAclOffCommand>"0x15, 0x01, 0x00, 0x00, 0x0a, 0x00, 0x02, 0x55, 0x00"</PanelAclOffCommand>

	<PanelAclLowCommand>"0x15, 0x01, 0x00, 0x00, 0x0a, 0x00, 0x02, 0x55, 0x03"</PanelAclLowCommand>

	<PanelAclMiddleCommand>"0x15, 0x01, 0x00, 0x00, 0x0a, 0x00, 0x02, 0x55, 0x02"</PanelAclMiddleCommand>

	<PanelAclHighCommand>"0x15, 0x01, 0x00, 0x00, 0x0a, 0x00, 0x02, 0x55, 0x01"</PanelAclHighCommand>

	<!-- Panel Aod cmd -->
	<PanelAodEnterCommand>"0x39, 0x01, 0x00, 0x00, 0x0a, 0x00, 0x02, 0xB0, 0xA1
				   0x05, 0x01, 0x00, 0x00, 0x0a, 0x00, 0x01, 0x12
				   0x39, 0x01, 0x00, 0x00, 0x0a, 0x00, 0x03, 0x51, 0x00, 0x00"</PanelAodEnterCommand>

	<PanelAodHighBrightnessCommand>"0x39, 0x01, 0x00, 0x00, 0x22, 0x01, 0x03, 0x51, 0x07, 0xFF"</PanelAodHighBrightnessCommand>

	<PanelAodLowBrightnessCommand>"0x39, 0x01, 0x00, 0x00, 0x22, 0x01, 0x03, 0x51, 0x05, 0xFF"</PanelAodLowBrightnessCommand>

	<PanelAodExitCommand>"0x39, 0x01, 0x00, 0x00, 0x0a, 0x00, 0x02, 0xB0, 0xA1
			       0x05, 0x01, 0x00, 0x00, 0x0a, 0x00, 0x01, 0x13
			       0x39, 0x01, 0x00, 0x00, 0x0a, 0x00, 0x03, 0x51, 0x00, 0x00"</PanelAodExitCommand>

	<PanelVersion>"V4,V4,V4,V4,V4,VN1"</PanelVersion>
	<PanelVersionCommand>"0x06, 0x01, 0x00, 0x00, 0x0a, 0x00, 0x09, 0xA0, 0x06, 0x00, 0x00, 0x00, 0x00, 0x00, 0x00, 0x00"</PanelVersionCommand>
	<PanelVersionValue>"0x4A, 0x43, 0x41
			0x4A, 0x43, 0x42
			0x4D, 0x55, 0x42
			0x4E, 0x4D, 0x4E
			0x4E, 0x4D, 0x50
			0x53, 0x44, 0x4C"</PanelVersionValue>

	<PanelTpColorCommand>"0x39, 0x01, 0x00, 0x00, 0x0a, 0x00, 0x02, 0xB0, 0xA6
			0x06, 0x01, 0x00, 0x00, 0x0a, 0x00, 0x01, 0xa9"</PanelTpColorCommand>

	<!-- Panel CE Command -->
	<PanelCeOffMode>""</PanelCeOffMode>
	<PanelCeSrgbMode>""</PanelCeSrgbMode>
	<PanelCeUserMode>""</PanelCeUserMode>
	<PanelCeVividMode>""</PanelCeVividMode>

	<!-- for esd check -->
	<PanelEsdRegCommand>"0x06, 0x01, 0x00, 0x00, 0x0a, 0x00, 0x01, 0x0a"</PanelEsdRegCommand>
	<PanelEsdValue>"0x9c"</PanelEsdValue>

	<!-- for mipi tr check -->
	<PanelCheckRegCommand>"0x06, 0x01, 0x00, 0x00, 0x0a, 0x00, 0x01, 0x0a"</PanelCheckRegCommand>
	<PanelCheckRegValue>"0x9c"</PanelCheckRegValue>

	<!-- for display region-->
	<PanelDirtyRegionCommand>"0x39, 0x01, 0x00, 0x00, 0x05, 0x00, 0x05, 0x2A, 0x00, 0x00, 0x04, 0x97
				0x39, 0x01, 0x00, 0x00, 0x05, 0x00, 0x05, 0x2B, 0x00, 0x00, 0x09, 0x5F"</PanelDirtyRegionCommand>

	<!-- 2d barcode support -->
	<Barcode2DCommand>"0x39, 0x01, 0x00, 0x00, 0x0a, 0x00, 0x02, 0xB0, 0xA5
				0x14, 0x01, 0x00, 0x00, 0x0a, 0x00, 0x1D, 0xB5, 0x00, 0x00, 0x00, 0x00, 0x00, 0x00, 0x00, 0x00, 0x00, 0x00, 0x00, 0x00, 0x00, 0x00, 0x00, 0x00, 0x00, 0x00, 0x00, 0x00, 0x00, 0x00, 0x00, 0x00, 0x00, 0x00, 0x00, 0x00"</Barcode2DCommand>

	<!-- for checksum -->
	<PanelChecksumEnterCommand>"0x15, 0x01, 0x00, 0x00, 0x64, 0x01, 0x02, 0xFF, 0x25
				0x15, 0x01, 0x00, 0x00, 0x0a, 0x00, 0x02, 0xFB, 0x01
				0x15, 0x01, 0x00, 0x00, 0x0a, 0x00, 0x02, 0x91, 0x1F
				0x15, 0x01, 0x00, 0x00, 0x0a, 0x00, 0x02, 0x92, 0x0F
				0x15, 0x01, 0x00, 0x00, 0x0a, 0x00, 0x02, 0x94, 0xA0
				0x15, 0x01, 0x00, 0x00, 0x0a, 0x00, 0x02, 0x95, 0x03
				0x15, 0x01, 0x00, 0x00, 0x0a, 0x00, 0x02, 0x96, 0x01
				0x15, 0x01, 0x00, 0x00, 0x0a, 0x00, 0x02, 0x97, 0x00
				0x15, 0x01, 0x00, 0x00, 0x0a, 0x00, 0x02, 0x98, 0x00
				0x15, 0x01, 0x00, 0x00, 0x0a, 0x00, 0x02, 0x93, 0x04"</PanelChecksumEnterCommand>
	<PanelChecksumEnableCommand>"0x15, 0x01, 0x00, 0x00, 0x0a, 0x00, 0x02, 0x93, 0x14
				0x15, 0x01, 0x00, 0x00, 0x0a, 0x00, 0x02, 0x99, 0xF8
				0x15, 0x01, 0x00, 0x00, 0x0a, 0x00, 0x02, 0x9A, 0x42
				0x15, 0x01, 0x00, 0x00, 0x0a, 0x00, 0x02, 0x9B, 0xA3
				0x15, 0x01, 0x00, 0x00, 0x0a, 0x00, 0x02, 0x9C, 0x03
				0x15, 0x01, 0x00, 0x00, 0x0a, 0x00, 0x02, 0x9D, 0xF2
				0x15, 0x01, 0x00, 0x00, 0x0a, 0x00, 0x02, 0x9E, 0xD9
				0x15, 0x01, 0x00, 0x00, 0x0a, 0x00, 0x02, 0x9F, 0x58
				0x15, 0x01, 0x00, 0x00, 0x0a, 0x00, 0x02, 0xA0, 0x00
				0x15, 0x01, 0x00, 0x00, 0x64, 0x01, 0x02, 0xFF, 0x10"</PanelChecksumEnableCommand>

	<!-- Panel pcd cmd -->
	<PanelPcdDetectOpenCommand>"0x39, 0x01, 0x00, 0x00, 0x0a, 0x00, 0x02, 0xB0, 0xA1
				0x39, 0x01, 0x00, 0x00, 0x11, 0x01, 0x04, 0x69, 0x00, 0x00, 0x03
				0x39, 0x01, 0x00, 0x00, 0x11, 0x01, 0x04, 0x69, 0x00, 0x00, 0x07
				0x39, 0x01, 0x00, 0x00, 0x11, 0x01, 0x04, 0x69, 0x00, 0x00, 0x0F"</PanelPcdDetectOpenCommand>
	<PanelPcdDetectCloseCommand>"0x39, 0x01, 0x00, 0x00, 0x0a, 0x00, 0x02, 0xB0, 0xA1
				0x39, 0x01, 0x00, 0x00, 0x0a, 0x01, 0x04, 0x69, 0x00, 0x00, 0x00 "</PanelPcdDetectCloseCommand>

</PanelEntry>
</hwlcd>
